freshstack/__init__.py
freshstack/logging.py
freshstack/util.py
freshstack/chunking/__init__.py
freshstack/chunking/chunk_corpus.py
freshstack/chunking/chunker.py
freshstack/chunking/data_manager.py
freshstack/chunking/util.py
freshstack/datasets/__init__.py
freshstack/datasets/data_loader.py
freshstack/datasets/util.py
freshstack/retrieval/__init__.py
freshstack/retrieval/evaluation.py
freshstack/retrieval/metrics.py
freshstack/retrieval/util.py
freshstack-0.0.6.dist-info/licenses/LICENSE
freshstack-0.0.6.dist-info/METADATA
freshstack-0.0.6.dist-info/WHEEL
freshstack-0.0.6.dist-info/top_level.txt
freshstack-0.0.6.dist-info/RECORD
