Metadata-Version: 2.4
Name: freshstack
Version: 0.0.6
Summary: A framework to generate realistic IR & RAG Benchmarks.
Author-email: Nandan Thakur <nandant@gmail.com>, Andrew Drozdov <andrew.drozdov@databricks.com>, Omar Khattab <omar.khattab@databricks.com>
Maintainer-email: Nandan Thakur <nandant@gmail.com>
License: Apache License 2.0
Project-URL: Homepage, https://fresh-stack.github.io/
Project-URL: Repository, https://github.com/fresh-stack/freshstack
Project-URL: Download, https://github.com/fresh-stack/freshstack/archive/v0.0.5.zip
Keywords: Benchmarking,Evaluation Framework,Information Retrieval,Retrieval-Augmented Generation,Transformer Networks,Large Language Models,PyTorch,RAG,IR,NLP,Deep Learning
Classifier: Development Status :: 4 - Beta
Classifier: Intended Audience :: Science/Research
Classifier: License :: OSI Approved :: Apache Software License
Classifier: Programming Language :: Python :: 3.9
Classifier: Programming Language :: Python :: 3.10
Classifier: Programming Language :: Python :: 3.11
Classifier: Programming Language :: Python :: 3.12
Classifier: Topic :: Scientific/Engineering :: Artificial Intelligence
Requires-Python: >=3.9
License-File: LICENSE
Requires-Dist: pyndeval
Requires-Dist: pytrec-eval-terrier
Requires-Dist: datasets
Provides-Extra: eval
Requires-Dist: beir; extra == "eval"
Requires-Dist: pylate; extra == "eval"
Provides-Extra: dev
Requires-Dist: beir; extra == "dev"
Requires-Dist: pylate; extra == "dev"
Requires-Dist: lxml; extra == "dev"
Requires-Dist: beautifulsoup4; extra == "dev"
Requires-Dist: py7zr; extra == "dev"
Requires-Dist: pymupdf4llm; extra == "dev"
Requires-Dist: nbformat; extra == "dev"
Requires-Dist: nbconvert; extra == "dev"
Requires-Dist: pygments; extra == "dev"
Requires-Dist: tiktoken; extra == "dev"
Requires-Dist: gitpython; extra == "dev"
Requires-Dist: semchunk; extra == "dev"
Requires-Dist: tree-sitter; extra == "dev"
Requires-Dist: tree-sitter-language-pack; extra == "dev"
Dynamic: license-file
